specmatic/__init__.py
specmatic/build_utils.py
specmatic/utils.py
specmatic/version.py
specmatic/core/__init__.py
specmatic/core/decorators.py
specmatic/core/specmatic.jar
specmatic/core/specmatic.py
specmatic/core/specmatic_base.py
specmatic/core/specmatic_mock.py
specmatic/core/specmatic_test.py
specmatic/coverage/__init__.py
specmatic/coverage/app_route_adapter.py
specmatic/coverage/coverage_route.py
specmatic/coverage/fastapi_app_route_adapter.py
specmatic/coverage/flask_app_route_adapter.py
specmatic/coverage/sanic_app_route_adapter.py
specmatic/coverage/servers/__init__.py
specmatic/coverage/servers/coverage_server.py
specmatic/coverage/servers/fastapi_app_coverage_server.py
specmatic/coverage/servers/flask_app_coverage_server.py
specmatic/coverage/servers/sanic_app_coverage_server.py
specmatic/generators/__init__.py
specmatic/generators/pytest_generator.py
specmatic/generators/test_generator_base.py
specmatic/generators/unittest_generator.py
specmatic/servers/__init__.py
specmatic/servers/app_server.py
specmatic/servers/asgi_app_server.py
specmatic/servers/wsgi_app_server.py
specmatic/servers/wsgi_server_thread.py
specmatic-2.36.1.post1.dist-info/METADATA
specmatic-2.36.1.post1.dist-info/WHEEL
specmatic-2.36.1.post1.dist-info/top_level.txt
specmatic-2.36.1.post1.dist-info/RECORD
