Metadata-Version: 2.4
Name: specmatic
Version: 2.36.1.post1
Summary: A Python module for using the Specmatic Library.
Home-page: https://github.com/specmatic/specmatic-python-extensions
Author: Specmatic Builders
Author-email: info@core.in
License: MIT
Requires-Python: >=3.11
Requires-Dist: pytest>=7.3.1
Requires-Dist: requests>=2.32.4
Requires-Dist: Werkzeug>=3.1.4
Requires-Dist: uvicorn>=0.18.0
Requires-Dist: fastapi>=0.70.0
Requires-Dist: flask>=2.2.5
Requires-Dist: sanic>=22.12.0
Dynamic: author
Dynamic: author-email
Dynamic: description
Dynamic: description-content-type
Dynamic: home-page
Dynamic: license
Dynamic: requires-dist
Dynamic: requires-python
Dynamic: summary
